alibabacloud_cams20200606/__init__.py
alibabacloud_cams20200606/client.py
alibabacloud_cams20200606/models/__init__.py
alibabacloud_cams20200606/models/_add_address_recover_suspend_request.py
alibabacloud_cams20200606/models/_add_address_recover_suspend_response.py
alibabacloud_cams20200606/models/_add_address_recover_suspend_response_body.py
alibabacloud_cams20200606/models/_add_address_recover_suspend_shrink_request.py
alibabacloud_cams20200606/models/_add_audit_viber_open_request.py
alibabacloud_cams20200606/models/_add_audit_viber_open_response.py
alibabacloud_cams20200606/models/_add_audit_viber_open_response_body.py
alibabacloud_cams20200606/models/_add_audit_viber_open_shrink_request.py
alibabacloud_cams20200606/models/_add_chat_group_invite_link_request.py
alibabacloud_cams20200606/models/_add_chat_group_invite_link_response.py
alibabacloud_cams20200606/models/_add_chat_group_invite_link_response_body.py
alibabacloud_cams20200606/models/_add_chat_group_request.py
alibabacloud_cams20200606/models/_add_chat_group_response.py
alibabacloud_cams20200606/models/_add_chat_group_response_body.py
alibabacloud_cams20200606/models/_add_chatapp_phone_number_request.py
alibabacloud_cams20200606/models/_add_chatapp_phone_number_response.py
alibabacloud_cams20200606/models/_add_chatapp_phone_number_response_body.py
alibabacloud_cams20200606/models/_add_contacts_request.py
alibabacloud_cams20200606/models/_add_contacts_response.py
alibabacloud_cams20200606/models/_add_contacts_response_body.py
alibabacloud_cams20200606/models/_add_contacts_shrink_request.py
alibabacloud_cams20200606/models/_add_custom_audience_user_request.py
alibabacloud_cams20200606/models/_add_custom_audience_user_response.py
alibabacloud_cams20200606/models/_add_custom_audience_user_response_body.py
alibabacloud_cams20200606/models/_add_custom_audience_user_shrink_request.py
alibabacloud_cams20200606/models/_add_group_request.py
alibabacloud_cams20200606/models/_add_group_response.py
alibabacloud_cams20200606-4.1.0.dist-info/LICENSE
alibabacloud_cams20200606-4.1.0.dist-info/METADATA
alibabacloud_cams20200606-4.1.0.dist-info/WHEEL
alibabacloud_cams20200606-4.1.0.dist-info/top_level.txt
alibabacloud_cams20200606-4.1.0.dist-info/RECORD
